{
  "firstName": "JILL",
  "lastName": "BARGONETTI-CHAVARRIA",
  "courses": [
    {
      "semester": "Spring 2014",
      "subject": "BIOL 47111 Sec: 01",
      "questions": [
        {
          "average": "5.5",
          "id": 1,
          "question": "Provides clearly defined objectives for students."
        },
        {
          "average": "5.25",
          "id": 2,
          "question": "Treats all students in a respectful manner."
        },
        {
          "average": "5.75",
          "id": 3,
          "question": "Presents course content in an organized manner."
        },
        {
          "average": "5.5",
          "id": 4,
          "question": "Makes good use of examples and illustrations to clarify concepts."
        },
        {
          "average": "6",
          "id": 5,
          "question": "Interprets difficult and abstract ideas."
        },
        {
          "average": "6.25",
          "id": 6,
          "question": "Effectively communicates his/her knowledge of the subject to students."
        },
        {
          "average": "6.75",
          "id": 7,
          "question": "Challenges me intellectually."
        },
        {
          "average": "6.75",
          "id": 8,
          "question": "Has increased my interest in the subject."
        },
        {
          "average": "6",
          "id": 9,
          "question": "My overall evaluation of this instructor's teaching."
        },
        {
          "average": "2.75",
          "id": 10,
          "question": "As much as possible, did the instructor provide individual attention?"
        },
        {
          "average": "3",
          "id": 11,
          "question": "As much as possible, did the instructor encourage student participation?"
        },
        {
          "average": "2.75",
          "id": 12,
          "question": "As much as possible, did the instructor provide constructive feedback on work submitted?"
        },
        {
          "average": "2.75",
          "id": 13,
          "question": "How helpful to you were instructor's responses to questions that you asked?"
        },
        {
          "average": "2.67",
          "id": 14,
          "question": "Did supplemental materials (for example, website, audio/visual aids, etc.) enhance course content?"
        },
        {
          "id": 15,
          "no": "0",
          "noAnswer": "0",
          "question": "Did exams and assignments reflect materials emphasized in course?",
          "yes": "4"
        },
        {
          "id": 16,
          "no": "0",
          "noAnswer": "0",
          "question": "Did the syllabus or other documents accurately reflect course content and grading?",
          "yes": "4"
        },
        {
          "id": 17,
          "no": "0",
          "noAnswer": "0",
          "question": "Did the instructor begin and end class on time?",
          "yes": "4"
        },
        {
          "id": 18,
          "no": "0",
          "noAnswer": "0",
          "question": "Was your work graded fairly?",
          "yes": "4"
        },
        {
          "id": 19,
          "no": "0",
          "noAnswer": "0",
          "question": "Did the instructor return graded material in a timely manner?",
          "yes": "4"
        },
        {
          "id": 20,
          "no": "0",
          "noAnswer": "0",
          "question": "Did the instructor keep his or her office hours?",
          "yes": "4"
        },
        {
          "A": "4",
          "B": "0",
          "C": "0",
          "CREDIT / NO CREDIT": "0",
          "D": "0",
          "F": "0",
          "id": 21,
          "question": "Grade you expect in this course"
        }
      ]
    },
    {
      "semester": "Spring 2014",
      "subject": "BIOL 79011 Sec: 01",
      "questions": [
        {
          "average": "6",
          "id": 1,
          "question": "Provides clearly defined objectives for students."
        },
        {
          "average": "6",
          "id": 2,
          "question": "Treats all students in a respectful manner."
        },
        {
          "average": "6",
          "id": 3,
          "question": "Presents course content in an organized manner."
        },
        {
          "average": "6",
          "id": 4,
          "question": "Makes good use of examples and illustrations to clarify concepts."
        },
        {
          "average": "6",
          "id": 5,
          "question": "Interprets difficult and abstract ideas."
        },
        {
          "average": "6",
          "id": 6,
          "question": "Effectively communicates his/her knowledge of the subject to students."
        },
        {
          "average": "6",
          "id": 7,
          "question": "Challenges me intellectually."
        },
        {
          "average": "6",
          "id": 8,
          "question": "Has increased my interest in the subject."
        },
        {
          "average": "6",
          "id": 9,
          "question": "My overall evaluation of this instructor's teaching."
        },
        {
          "average": "3",
          "id": 10,
          "question": "As much as possible, did the instructor provide individual attention?"
        },
        {
          "average": "3",
          "id": 11,
          "question": "As much as possible, did the instructor encourage student participation?"
        },
        {
          "average": "3",
          "id": 12,
          "question": "As much as possible, did the instructor provide constructive feedback on work submitted?"
        },
        {
          "average": "3",
          "id": 13,
          "question": "How helpful to you were instructor's responses to questions that you asked?"
        },
        {
          "average": " ",
          "id": 14,
          "question": "Did supplemental materials (for example, website, audio/visual aids, etc.) enhance course content?"
        },
        {
          "id": 15,
          "no": "0",
          "noAnswer": "0",
          "question": "Did exams and assignments reflect materials emphasized in course?",
          "yes": "1"
        },
        {
          "id": 16,
          "no": "0",
          "noAnswer": "0",
          "question": "Did the syllabus or other documents accurately reflect course content and grading?",
          "yes": "1"
        },
        {
          "id": 17,
          "no": "0",
          "noAnswer": "0",
          "question": "Did the instructor begin and end class on time?",
          "yes": "1"
        },
        {
          "id": 18,
          "no": "0",
          "noAnswer": "0",
          "question": "Was your work graded fairly?",
          "yes": "1"
        },
        {
          "id": 19,
          "no": "0",
          "noAnswer": "0",
          "question": "Did the instructor return graded material in a timely manner?",
          "yes": "1"
        },
        {
          "id": 20,
          "no": "0",
          "noAnswer": "0",
          "question": "Did the instructor keep his or her office hours?",
          "yes": "1"
        },
        {
          "A": "1",
          "B": "0",
          "C": "0",
          "CREDIT / NO CREDIT": "0",
          "D": "0",
          "F": "0",
          "id": 21,
          "question": "Grade you expect in this course"
        }
      ]
    },
    {
      "semester": "Fall 2014",
      "subject": "BIOL 30300 Sec: 01",
      "questions": [
        {
          "average": "5.89",
          "id": 1,
          "question": "Provides clearly defined objectives for students."
        },
        {
          "average": "6.22",
          "id": 2,
          "question": "Treats all students in a respectful manner."
        },
        {
          "average": "5.84",
          "id": 3,
          "question": "Presents course content in an organized manner."
        },
        {
          "average": "5.86",
          "id": 4,
          "question": "Makes good use of examples and illustrations to clarify concepts."
        },
        {
          "average": "5.92",
          "id": 5,
          "question": "Interprets difficult and abstract ideas."
        },
        {
          "average": "6.03",
          "id": 6,
          "question": "Effectively communicates his/her knowledge of the subject to students."
        },
        {
          "average": "6.03",
          "id": 7,
          "question": "Challenges me intellectually."
        },
        {
          "average": "5.97",
          "id": 8,
          "question": "Has increased my interest in the subject."
        },
        {
          "average": "5.84",
          "id": 9,
          "question": "My overall evaluation of this instructor's teaching."
        },
        {
          "average": "2.66",
          "id": 10,
          "question": "As much as possible, did the instructor provide individual attention?"
        },
        {
          "average": "2.83",
          "id": 11,
          "question": "As much as possible, did the instructor encourage student participation?"
        },
        {
          "average": "2.54",
          "id": 12,
          "question": "As much as possible, did the instructor provide constructive feedback on work submitted?"
        },
        {
          "average": "2.71",
          "id": 13,
          "question": "How helpful to you were instructor's responses to questions that you asked?"
        },
        {
          "average": "2.65",
          "id": 14,
          "question": "Did supplemental materials (for example, website, audio/visual aids, etc.) enhance course content?"
        },
        {
          "id": 15,
          "no": "1",
          "noAnswer": "0",
          "question": "Did exams and assignments reflect materials emphasized in course?",
          "yes": "36"
        },
        {
          "id": 16,
          "no": "1",
          "noAnswer": "0",
          "question": "Did the syllabus or other documents accurately reflect course content and grading?",
          "yes": "36"
        },
        {
          "id": 17,
          "no": "0",
          "noAnswer": "0",
          "question": "Did the instructor begin and end class on time?",
          "yes": "37"
        },
        {
          "id": 18,
          "no": "0",
          "noAnswer": "0",
          "question": "Was your work graded fairly?",
          "yes": "37"
        },
        {
          "id": 19,
          "no": "1",
          "noAnswer": "1",
          "question": "Did the instructor return graded material in a timely manner?",
          "yes": "35"
        },
        {
          "id": 20,
          "no": "0",
          "noAnswer": "3",
          "question": "Did the instructor keep his or her office hours?",
          "yes": "34"
        },
        {
          "A": "22",
          "B": "10",
          "C": "4",
          "CREDIT / NO CREDIT": "0",
          "D": "1",
          "F": "0",
          "id": 21,
          "question": "Grade you expect in this course"
        }
      ]
    },
    {
      "semester": "Spring 2015",
      "subject": "BIOL 17500 Sec: HC1",
      "questions": [
        {
          "average": "6",
          "id": 1,
          "question": "Provides clearly defined objectives for students."
        },
        {
          "average": "6.25",
          "id": 2,
          "question": "Treats all students in a respectful manner."
        },
        {
          "average": "6",
          "id": 3,
          "question": "Presents course content in an organized manner."
        },
        {
          "average": "6.5",
          "id": 4,
          "question": "Makes good use of examples and illustrations to clarify concepts."
        },
        {
          "average": "6.75",
          "id": 5,
          "question": "Interprets difficult and abstract ideas."
        },
        {
          "average": "5.25",
          "id": 6,
          "question": "Effectively communicates his/her knowledge of the subject to students."
        },
        {
          "average": "6.25",
          "id": 7,
          "question": "Challenges me intellectually."
        },
        {
          "average": "6",
          "id": 8,
          "question": "Has increased my interest in the subject."
        },
        {
          "average": "6.25",
          "id": 9,
          "question": "My overall evaluation of this instructor's teaching."
        },
        {
          "average": "3",
          "id": 10,
          "question": "As much as possible, did the instructor provide individual attention?"
        },
        {
          "average": "3",
          "id": 11,
          "question": "As much as possible, did the instructor encourage student participation?"
        },
        {
          "average": "3",
          "id": 12,
          "question": "As much as possible, did the instructor provide constructive feedback on work submitted?"
        },
        {
          "average": "2.75",
          "id": 13,
          "question": "How helpful to you were instructor's responses to questions that you asked?"
        },
        {
          "average": "3",
          "id": 14,
          "question": "Did supplemental materials (for example, website, audio/visual aids, etc.) enhance course content?"
        },
        {
          "id": 15,
          "no": "0",
          "noAnswer": "0",
          "question": "Did exams and assignments reflect materials emphasized in course?",
          "yes": "4"
        },
        {
          "id": 16,
          "no": "0",
          "noAnswer": "0",
          "question": "Did the syllabus or other documents accurately reflect course content and grading?",
          "yes": "4"
        },
        {
          "id": 17,
          "no": "0",
          "noAnswer": "0",
          "question": "Did the instructor begin and end class on time?",
          "yes": "4"
        },
        {
          "id": 18,
          "no": "0",
          "noAnswer": "0",
          "question": "Was your work graded fairly?",
          "yes": "4"
        },
        {
          "id": 19,
          "no": "0",
          "noAnswer": "0",
          "question": "Did the instructor return graded material in a timely manner?",
          "yes": "4"
        },
        {
          "id": 20,
          "no": "0",
          "noAnswer": "0",
          "question": "Did the instructor keep his or her office hours?",
          "yes": "4"
        },
        {
          "A": "4",
          "B": "0",
          "C": "0",
          "CREDIT / NO CREDIT": "0",
          "D": "0",
          "F": "0",
          "id": 21,
          "question": "Grade you expect in this course"
        }
      ]
    },
    {
      "semester": "Fall 2015",
      "subject": "BIOL 17500 Sec: 01",
      "questions": [
        {
          "average": "5.33",
          "id": 1,
          "question": "Provides clearly defined objectives for students."
        },
        {
          "average": "5.89",
          "id": 2,
          "question": "Treats all students in a respectful manner."
        },
        {
          "average": "5.33",
          "id": 3,
          "question": "Presents course content in an organized manner."
        },
        {
          "average": "5.78",
          "id": 4,
          "question": "Makes good use of examples and illustrations to clarify concepts."
        },
        {
          "average": "5.78",
          "id": 5,
          "question": "Interprets difficult and abstract ideas."
        },
        {
          "average": "5.89",
          "id": 6,
          "question": "Effectively communicates his/her knowledge of the subject to students."
        },
        {
          "average": "6.33",
          "id": 7,
          "question": "Challenges me intellectually."
        },
        {
          "average": "5.44",
          "id": 8,
          "question": "Has increased my interest in the subject."
        },
        {
          "average": "5.67",
          "id": 9,
          "question": "My overall evaluation of this instructor's teaching."
        },
        {
          "average": "2.78",
          "id": 10,
          "question": "As much as possible, did the instructor provide individual attention?"
        },
        {
          "average": "2.78",
          "id": 11,
          "question": "As much as possible, did the instructor encourage student participation?"
        },
        {
          "average": "3",
          "id": 12,
          "question": "As much as possible, did the instructor provide constructive feedback on work submitted?"
        },
        {
          "average": "2.78",
          "id": 13,
          "question": "How helpful to you were instructor's responses to questions that you asked?"
        },
        {
          "average": "2.88",
          "id": 14,
          "question": "Did supplemental materials (for example, website, audio/visual aids, etc.) enhance course content?"
        },
        {
          "id": 15,
          "no": "1",
          "noAnswer": "0",
          "question": "Did exams and assignments reflect materials emphasized in course?",
          "yes": "8"
        },
        {
          "id": 16,
          "no": "0",
          "noAnswer": "0",
          "question": "Did the syllabus or other documents accurately reflect course content and grading?",
          "yes": "9"
        },
        {
          "id": 17,
          "no": "0",
          "noAnswer": "0",
          "question": "Did the instructor begin and end class on time?",
          "yes": "9"
        },
        {
          "id": 18,
          "no": "0",
          "noAnswer": "0",
          "question": "Was your work graded fairly?",
          "yes": "9"
        },
        {
          "id": 19,
          "no": "0",
          "noAnswer": "0",
          "question": "Did the instructor return graded material in a timely manner?",
          "yes": "9"
        },
        {
          "id": 20,
          "no": "0",
          "noAnswer": "1",
          "question": "Did the instructor keep his or her office hours?",
          "yes": "8"
        },
        {
          "A": "8",
          "B": "1",
          "C": "0",
          "CREDIT / NO CREDIT": "0",
          "D": "0",
          "F": "0",
          "id": 21,
          "question": "Grade you expect in this course"
        }
      ]
    },
    {
      "semester": "Spring 2016",
      "subject": "BIOL 30300 Sec: 01",
      "questions": [
        {
          "average": "5.79",
          "id": 1,
          "question": "Provides clearly defined objectives for students."
        },
        {
          "average": "5.97",
          "id": 2,
          "question": "Treats all students in a respectful manner."
        },
        {
          "average": "5.34",
          "id": 3,
          "question": "Presents course content in an organized manner."
        },
        {
          "average": "5.97",
          "id": 4,
          "question": "Makes good use of examples and illustrations to clarify concepts."
        },
        {
          "average": "5.9",
          "id": 5,
          "question": "Interprets difficult and abstract ideas."
        },
        {
          "average": "5.83",
          "id": 6,
          "question": "Effectively communicates his/her knowledge of the subject to students."
        },
        {
          "average": "5.83",
          "id": 7,
          "question": "Challenges me intellectually."
        },
        {
          "average": "5.62",
          "id": 8,
          "question": "Has increased my interest in the subject."
        },
        {
          "average": "5.86",
          "id": 9,
          "question": "My overall evaluation of this instructor's teaching."
        },
        {
          "average": "2.73",
          "id": 10,
          "question": "As much as possible, did the instructor provide individual attention?"
        },
        {
          "average": "2.89",
          "id": 11,
          "question": "As much as possible, did the instructor encourage student participation?"
        },
        {
          "average": "2.58",
          "id": 12,
          "question": "As much as possible, did the instructor provide constructive feedback on work submitted?"
        },
        {
          "average": "2.76",
          "id": 13,
          "question": "How helpful to you were instructor's responses to questions that you asked?"
        },
        {
          "average": "2.69",
          "id": 14,
          "question": "Did supplemental materials (for example, website, audio/visual aids, etc.) enhance course content?"
        },
        {
          "id": 15,
          "no": "1",
          "noAnswer": "0",
          "question": "Did exams and assignments reflect materials emphasized in course?",
          "yes": "28"
        },
        {
          "id": 16,
          "no": "0",
          "noAnswer": "0",
          "question": "Did the syllabus or other documents accurately reflect course content and grading?",
          "yes": "29"
        },
        {
          "id": 17,
          "no": "2",
          "noAnswer": "0",
          "question": "Did the instructor begin and end class on time?",
          "yes": "27"
        },
        {
          "id": 18,
          "no": "1",
          "noAnswer": "2",
          "question": "Was your work graded fairly?",
          "yes": "26"
        },
        {
          "id": 19,
          "no": "1",
          "noAnswer": "2",
          "question": "Did the instructor return graded material in a timely manner?",
          "yes": "26"
        },
        {
          "id": 20,
          "no": "0",
          "noAnswer": "4",
          "question": "Did the instructor keep his or her office hours?",
          "yes": "25"
        },
        {
          "A": "13",
          "B": "13",
          "C": "3",
          "CREDIT / NO CREDIT": "0",
          "D": "0",
          "F": "0",
          "id": 21,
          "question": "Grade you expect in this course"
        }
      ]
    },
    {
      "semester": "Fall 2016",
      "subject": "BIOL 17500 Sec: HC1",
      "questions": [
        {
          "average": "6.2",
          "id": 1,
          "question": "Provides clearly defined objectives for students."
        },
        {
          "average": "6.4",
          "id": 2,
          "question": "Treats all students in a respectful manner."
        },
        {
          "average": "6",
          "id": 3,
          "question": "Presents course content in an organized manner."
        },
        {
          "average": "6.4",
          "id": 4,
          "question": "Makes good use of examples and illustrations to clarify concepts."
        },
        {
          "average": "6.8",
          "id": 5,
          "question": "Interprets difficult and abstract ideas."
        },
        {
          "average": "6",
          "id": 6,
          "question": "Effectively communicates his/her knowledge of the subject to students."
        },
        {
          "average": "6.4",
          "id": 7,
          "question": "Challenges me intellectually."
        },
        {
          "average": "5.6",
          "id": 8,
          "question": "Has increased my interest in the subject."
        },
        {
          "average": "6",
          "id": 9,
          "question": "My overall evaluation of this instructor's teaching."
        },
        {
          "average": "2.6",
          "id": 10,
          "question": "As much as possible, did the instructor provide individual attention?"
        },
        {
          "average": "3",
          "id": 11,
          "question": "As much as possible, did the instructor encourage student participation?"
        },
        {
          "average": "3",
          "id": 12,
          "question": "As much as possible, did the instructor provide constructive feedback on work submitted?"
        },
        {
          "average": "2.8",
          "id": 13,
          "question": "How helpful to you were instructor's responses to questions that you asked?"
        },
        {
          "average": "3",
          "id": 14,
          "question": "Did supplemental materials (for example, website, audio/visual aids, etc.) enhance course content?"
        },
        {
          "id": 15,
          "no": "0",
          "noAnswer": "0",
          "question": "Did exams and assignments reflect materials emphasized in course?",
          "yes": "5"
        },
        {
          "id": 16,
          "no": "0",
          "noAnswer": "0",
          "question": "Did the syllabus or other documents accurately reflect course content and grading?",
          "yes": "5"
        },
        {
          "id": 17,
          "no": "0",
          "noAnswer": "0",
          "question": "Did the instructor begin and end class on time?",
          "yes": "5"
        },
        {
          "id": 18,
          "no": "0",
          "noAnswer": "0",
          "question": "Was your work graded fairly?",
          "yes": "5"
        },
        {
          "id": 19,
          "no": "0",
          "noAnswer": "0",
          "question": "Did the instructor return graded material in a timely manner?",
          "yes": "5"
        },
        {
          "id": 20,
          "no": "0",
          "noAnswer": "1",
          "question": "Did the instructor keep his or her office hours?",
          "yes": "4"
        },
        {
          "A": "4",
          "B": "1",
          "C": "0",
          "CREDIT / NO CREDIT": "0",
          "D": "0",
          "F": "0",
          "id": 21,
          "question": "Grade you expect in this course"
        }
      ]
    }
  ]
}